MANIFEST.in
setup.py
Auto_Python_2014.egg-info/PKG-INFO
Auto_Python_2014.egg-info/SOURCES.txt
Auto_Python_2014.egg-info/dependency_links.txt
Auto_Python_2014.egg-info/not-zip-safe
Auto_Python_2014.egg-info/requires.txt
Auto_Python_2014.egg-info/top_level.txt
common/COM_database.py
common/COM_db_mysql.py
common/COM_httpclient.py
common/COM_util_tools.py
common/COM_util_trans.py
common/__init__.py
component/CPT_api_request.py
component/CPT_driver_cases.py
component/__init__.py
init/__init__.py
init/init_value.py
lib/HTMLTestRunner.py
lib/__init__.py
reporter/__init__.py
testCase/MobileTest.py
testCase/__init__.py
testCase/htmltestRunner.py
testCase/htmltestRunnerForMobile.py
testCase/testAutoCreateMethod.py
testCase/testDataDriver.py
testCase/testDataDriverForMobile.py
testCase/testDataProviderMetaclass.py
testCase/testParam.py
testCase/testunittest_data_provider.py
tools/__init__.py
tools/get-pip.py
util/__init__.py
util/escape.py
util/util.py